{
  "type": "FeatureCollection",
  "features": [
    {
      "type": "Feature",
      "properties": {
        "id": 213,
        "shape": "Line"
      },
      "geometry": {
        "type": "LineString",
        "coordinates": [
          [
            -82.900412,
            29.466283
          ],
          [
            -82.968578,
            29.455961
          ]
        ]
      }
    },
    {
      "type": "Feature",
      "properties": {
        "id": 216,
        "shape": "Line"
      },
      "geometry": {
        "type": "LineString",
        "coordinates": [
          [
            -82.995252,
            29.450798
          ],
          [
            -83.063419,
            29.440476
          ]
        ]
      }
    },
    {
      "type": "Feature",
      "properties": {
        "id": 218,
        "shape": "Line"
      },
      "geometry": {
        "type": "LineString",
        "coordinates": [
          [
            -83.090834,
            29.435957
          ],
          [
            -83.159,
            29.425635
          ]
        ]
      }
    },
    {
      "type": "Feature",
      "properties": {
        "id": 220,
        "shape": "Line"
      },
      "geometry": {
        "type": "LineString",
        "coordinates": [
          [
            -83.195306,
            29.416595
          ],
          [
            -83.263473,
            29.406273
          ]
        ]
      }
    },
    {
      "type": "Feature",
      "properties": {
        "id": 222,
        "shape": "Line"
      },
      "geometry": {
        "type": "LineString",
        "coordinates": [
          [
            -83.293111,
            29.399811
          ],
          [
            -83.361277,
            29.389489
          ]
        ]
      }
    },
    {
      "type": "Feature",
      "properties": {
        "id": 224,
        "shape": "Line"
      },
      "geometry": {
        "type": "LineString",
        "coordinates": [
          [
            -83.405549,
            29.379797
          ],
          [
            -83.473715,
            29.369475
          ]
        ]
      }
    },
    {
      "type": "Feature",
      "properties": {
        "id": 226,
        "shape": "Line"
      },
      "geometry": {
        "type": "LineString",
        "coordinates": [
          [
            -83.510021,
            29.362362
          ],
          [
            -83.578188,
            29.35204
          ]
        ]
      }
    },
    {
      "type": "Feature",
      "properties": {
        "id": 228,
        "shape": "Line"
      },
      "geometry": {
        "type": "LineString",
        "coordinates": [
          [
            -83.607085,
            29.346861
          ],
          [
            -83.675251,
            29.336539
          ]
        ]
      }
    },
    {
      "type": "Feature",
      "properties": {
        "id": 230,
        "shape": "Line"
      },
      "geometry": {
        "type": "LineString",
        "coordinates": [
          [
            -83.71378,
            29.327482
          ],
          [
            -83.781947,
            29.31716
          ]
        ]
      }
    },
    {
      "type": "Feature",
      "properties": {
        "id": 232,
        "shape": "Line"
      },
      "geometry": {
        "type": "LineString",
        "coordinates": [
          [
            -83.823254,
            29.309392
          ],
          [
            -83.891421,
            29.29907
          ]
        ]
      }
    },
    {
      "type": "Feature",
      "properties": {
        "id": 234,
        "shape": "Line"
      },
      "geometry": {
        "type": "LineString",
        "coordinates": [
          [
            -83.940323,
            29.290006
          ],
          [
            -84.00849,
            29.279684
          ]
        ]
      }
    },
    {
      "type": "Feature",
      "properties": {
        "id": 236,
        "shape": "Line"
      },
      "geometry": {
        "type": "LineString",
        "coordinates": [
          [
            -82.900782,
            29.487569
          ],
          [
            -82.8993,
            29.525614
          ]
        ]
      }
    },
    {
      "type": "Feature",
      "properties": {
        "id": 238,
        "shape": "Line"
      },
      "geometry": {
        "type": "LineString",
        "coordinates": [
          [
            -82.900782,
            29.553968
          ],
          [
            -82.8993,
            29.592013
          ]
        ]
      }
    },
    {
      "type": "Feature",
      "properties": {
        "id": 240,
        "shape": "Line"
      },
      "geometry": {
        "type": "LineString",
        "coordinates": [
          [
            -82.900782,
            29.624187
          ],
          [
            -82.8993,
            29.662232
          ]
        ]
      }
    },
    {
      "type": "Feature",
      "properties": {
        "id": 242,
        "shape": "Line"
      },
      "geometry": {
        "type": "LineString",
        "coordinates": [
          [
            -82.900782,
            29.698861
          ],
          [
            -82.8993,
            29.736907
          ]
        ]
      }
    },
    {
      "type": "Feature",
      "properties": {
        "id": 244,
        "shape": "Line"
      },
      "geometry": {
        "type": "LineString",
        "coordinates": [
          [
            -82.901523,
            29.763192
          ],
          [
            -82.900041,
            29.801237
          ]
        ]
      }
    },
    {
      "type": "Feature",
      "properties": {
        "id": 246,
        "shape": "Line"
      },
      "geometry": {
        "type": "LineString",
        "coordinates": [
          [
            -82.867625,
            29.800856
          ],
          [
            -82.820205,
            29.79957
          ]
        ]
      }
    },
    {
      "type": "Feature",
      "properties": {
        "id": 248,
        "shape": "Line"
      },
      "geometry": {
        "type": "LineString",
        "coordinates": [
          [
            -82.78464,
            29.801499
          ],
          [
            -82.737219,
            29.800213
          ]
        ]
      }
    },
    {
      "type": "Feature",
      "properties": {
        "id": 250,
        "shape": "Line"
      },
      "geometry": {
        "type": "LineString",
        "coordinates": [
          [
            -82.715732,
            29.802142
          ],
          [
            -82.668312,
            29.800856
          ]
        ]
      }
    },
    {
      "type": "Feature",
      "properties": {
        "id": 252,
        "shape": "Line"
      },
      "geometry": {
        "type": "LineString",
        "coordinates": [
          [
            -82.640156,
            29.815
          ],
          [
            -82.614223,
            29.832999
          ]
        ]
      }
    },
    {
      "type": "Feature",
      "properties": {
        "id": 254,
        "shape": "Line"
      },
      "geometry": {
        "type": "LineString",
        "coordinates": [
          [
            -82.586808,
            29.850991
          ],
          [
            -82.560875,
            29.86899
          ]
        ]
      }
    },
    {
      "type": "Feature",
      "properties": {
        "id": 256,
        "shape": "Line"
      },
      "geometry": {
        "type": "LineString",
        "coordinates": [
          [
            -82.53346,
            29.885685
          ],
          [
            -82.507527,
            29.903684
          ]
        ]
      }
    },
    {
      "type": "Feature",
      "properties": {
        "id": 258,
        "shape": "Line"
      },
      "geometry": {
        "type": "LineString",
        "coordinates": [
          [
            -82.479372,
            29.920366
          ],
          [
            -82.453439,
            29.938365
          ]
        ]
      }
    },
    {
      "type": "Feature",
      "properties": {
        "id": 260,
        "shape": "Line"
      },
      "geometry": {
        "type": "LineString",
        "coordinates": [
          [
            -82.424542,
            29.956962
          ],
          [
            -82.398609,
            29.97496
          ]
        ]
      }
    },
    {
      "type": "Feature",
      "properties": {
        "id": 262,
        "shape": "Line"
      },
      "geometry": {
        "type": "LineString",
        "coordinates": [
          [
            -82.366007,
            29.99611
          ],
          [
            -82.340075,
            30.014109
          ]
        ]
      }
    },
    {
      "type": "Feature",
      "properties": {
        "id": 264,
        "shape": "Line"
      },
      "geometry": {
        "type": "LineString",
        "coordinates": [
          [
            -82.314142,
            30.027546
          ],
          [
            -82.288209,
            30.045544
          ]
        ]
      }
    },
    {
      "type": "Feature",
      "properties": {
        "id": 266,
        "shape": "Line"
      },
      "geometry": {
        "type": "LineString",
        "coordinates": [
          [
            -82.266907,
            30.043919
          ],
          [
            -82.235046,
            30.031732
          ]
        ]
      }
    },
    {
      "type": "Feature",
      "properties": {
        "id": 268,
        "shape": "Line"
      },
      "geometry": {
        "type": "LineString",
        "coordinates": [
          [
            -82.210595,
            30.023391
          ],
          [
            -82.178734,
            30.011204
          ]
        ]
      }
    },
    {
      "type": "Feature",
      "properties": {
        "id": 270,
        "shape": "Line"
      },
      "geometry": {
        "type": "LineString",
        "coordinates": [
          [
            -82.149838,
            30.000292
          ],
          [
            -82.117977,
            29.988105
          ]
        ]
      }
    },
    {
      "type": "Feature",
      "properties": {
        "id": 272,
        "shape": "Line"
      },
      "geometry": {
        "type": "LineString",
        "coordinates": [
          [
            -82.084635,
            29.97462
          ],
          [
            -82.052774,
            29.962433
          ]
        ]
      }
    },
    {
      "type": "Feature",
      "properties": {
        "id": 274,
        "shape": "Line"
      },
      "geometry": {
        "type": "LineString",
        "coordinates": [
          [
            -82.00239,
            29.945731
          ],
          [
            -81.97053,
            29.933544
          ]
        ]
      }
    },
    {
      "type": "Feature",
      "properties": {
        "id": 276,
        "shape": "Line"
      },
      "geometry": {
        "type": "LineString",
        "coordinates": [
          [
            -82.043883,
            29.960498
          ],
          [
            -82.012023,
            29.948311
          ]
        ]
      }
    },
    {
      "type": "Feature",
      "properties": {
        "id": 11,
        "sector_name": "Brewton",
        "shape": "Polygon"
      },
      "geometry": {
        "type": "Polygon",
        "coordinates": [
          [
            [
              -88.030448,
              29.969848
            ],
            [
              -85.928882,
              29.967163
            ],
            [
              -85.689175,
              29.929562
            ],
            [
              -85.418472,
              29.63543
            ],
            [
              -85.368878,
              29.608484
            ],
            [
              -85.222161,
              29.613874
            ],
            [
              -85.081643,
              29.541988
            ],
            [
              -85.032048,
              29.536594
            ],
            [
              -84.930793,
              29.549179
            ],
            [
              -84.726216,
              29.648002
            ],
            [
              -84.678688,
              29.685709
            ],
            [
              -84.668356,
              29.705454
            ],
            [
              -84.327394,
              29.707249
            ],
            [
              -84.403852,
              29.847149
            ],
            [
              -84.521639,
              30.022643
            ],
            [
              -85.158101,
              30.715291
            ],
            [
              -85.88342,
              31.704116
            ],
            [
              -87.299833,
              31.417439
            ],
            [
              -87.399022,
              31.281222
            ],
            [
              -87.659264,
              30.955602
            ],
            [
              -87.683545,
              30.847886
            ],
            [
              -87.690777,
              30.792984
            ],
            [
              -87.716608,
              30.691527
            ],
            [
              -87.808564,
              30.683086
            ],
            [
              -87.91576,
              30.633906
            ],
            [
              -87.91576,
              30.522343
            ],
            [
              -88.023215,
              30.222828
            ],
            [
              -88.030448,
              29.969848
            ]
          ]
        ]
      }
    },
    {
      "type": "Feature",
      "properties": {
        "id": 30,
        "sector_name": "Nepta",
        "shape": "Polygon"
      },
      "geometry": {
        "type": "Polygon",
        "coordinates": [
          [
            [
              -83.733293,
              28.756036
            ],
            [
              -84.327394,
              29.707249
            ],
            [
              -84.668356,
              29.705454
            ],
            [
              -84.678688,
              29.685709
            ],
            [
              -84.726216,
              29.648002
            ],
            [
              -84.930793,
              29.549179
            ],
            [
              -85.032048,
              29.536594
            ],
            [
              -85.081643,
              29.541988
            ],
            [
              -85.222161,
              29.613874
            ],
            [
              -85.368878,
              29.608484
            ],
            [
              -85.418472,
              29.63543
            ],
            [
              -85.689175,
              29.929562
            ],
            [
              -85.928882,
              29.967163
            ],
            [
              -88.030448,
              29.969848
            ],
            [
              -88.001518,
              28.14193
            ],
            [
              -87.687419,
              27.49954
            ],
            [
              -86.001207,
              27.003533
            ],
            [
              -85.25729,
              27.495874
            ],
            [
              -84.943192,
              28.0444
            ],
            [
              -84.616695,
              28.062637
            ],
            [
              -83.733293,
              28.756036
            ]
          ]
        ]
      }
    },
    {
      "type": "Feature",
      "properties": {
        "id": 16,
        "sector_name": "Mayo",
        "shape": "Polygon"
      },
      "geometry": {
        "type": "Polygon",
        "coordinates": [
          [
            [
              -83.995539,
              28.550658
            ],
            [
              -83.52045,
              28.399452
            ],
            [
              -82.937715,
              27.947695
            ],
            [
              -82.388043,
              27.947695
            ],
            [
              -81.859035,
              28.184741
            ],
            [
              -81.710252,
              28.990374
            ],
            [
              -81.842504,
              29.509622
            ],
            [
              -81.867301,
              29.358447
            ],
            [
              -82.491365,
              29.28638
            ],
            [
              -82.867456,
              29.541988
            ],
            [
              -82.900519,
              29.174575
            ],
            [
              -83.52045,
              28.936134
            ],
            [
              -83.907776,
              29.036306
            ],
            [
              -83.733293,
              28.756036
            ],
            [
              -83.995539,
              28.550658
            ]
          ]
        ]
      }
    },
    {
      "type": "Feature",
      "properties": {
        "id": 75,
        "sector_name": "Greencove",
        "shape": "Polygon"
      },
      "geometry": {
        "type": "Polygon",
        "coordinates": [
          [
            [
              -81.492243,
              28.353999
            ],
            [
              -80.992165,
              28.719798
            ],
            [
              -81.269068,
              29.362049
            ],
            [
              -81.326928,
              30.297793
            ],
            [
              -81.335194,
              30.561497
            ],
            [
              -81.558285,
              30.820836
            ],
            [
              -81.558369,
              30.819163
            ],
            [
              -81.950992,
              30.463582
            ],
            [
              -82.050181,
              30.199613
            ],
            [
              -82.050588,
              30.198583
            ],
            [
              -81.843676,
              29.512621
            ],
            [
              -81.842504,
              29.509622
            ],
            [
              -81.710252,
              28.990374
            ],
            [
              -81.73508,
              28.856365
            ],
            [
              -81.492243,
              28.353999
            ]
          ]
        ]
      }
    },
    {
      "type": "Feature",
      "properties": {
        "id": 58,
        "sector_name": "St. Augustine",
        "shape": "Polygon"
      },
      "geometry": {
        "type": "Polygon",
        "coordinates": [
          [
            [
              -80.992165,
              28.719798
            ],
            [
              -80.731794,
              28.900863
            ],
            [
              -80.541682,
              28.929804
            ],
            [
              -80.108764,
              29.023807
            ],
            [
              -79.691344,
              30.5784
            ],
            [
              -80.968524,
              30.58197
            ],
            [
              -81.335091,
              30.558211
            ],
            [
              -81.326928,
              30.297793
            ],
            [
              -81.269068,
              29.362049
            ],
            [
              -80.992165,
              28.719798
            ]
          ]
        ]
      }
    },
    {
      "type": "Feature",
      "properties": {
        "id": 68,
        "sector_name": "States",
        "shape": "Polygon"
      },
      "geometry": {
        "type": "Polygon",
        "coordinates": [
          [
            [
              -80.86508,
              32.7842
            ],
            [
              -81.394087,
              32.401178
            ],
            [
              -81.409585,
              32.384601
            ],
            [
              -81.500509,
              32.027911
            ],
            [
              -81.500509,
              31.465592
            ],
            [
              -81.591432,
              31.275041
            ],
            [
              -81.54597,
              31.066405
            ],
            [
              -81.558285,
              30.820842
            ],
            [
              -81.335194,
              30.561497
            ],
            [
              -81.33509,
              30.558195
            ],
            [
              -80.968587,
              30.581966
            ],
            [
              -79.69621,
              30.578414
            ],
            [
              -79.295621,
              31.999
            ],
            [
              -80.225517,
              32.394198
            ],
            [
              -80.86508,
              32.7842
            ]
          ]
        ]
      }
    },
    {
      "type": "Feature",
      "properties": {
        "id": 17,
        "sector_name": "Perry",
        "shape": "Polygon"
      },
      "geometry": {
        "type": "Polygon",
        "coordinates": [
          [
            [
              -83.52045,
              28.936134
            ],
            [
              -82.900519,
              29.174575
            ],
            [
              -82.869549,
              29.518771
            ],
            [
              -82.871589,
              29.530302
            ],
            [
              -82.900519,
              29.674039
            ],
            [
              -83.214285,
              30.403127
            ],
            [
              -84.384221,
              30.289764
            ],
            [
              -84.909095,
              30.450223
            ],
            [
              -84.91607,
              30.452472
            ],
            [
              -84.521639,
              30.022643
            ],
            [
              -84.403852,
              29.847149
            ],
            [
              -84.327394,
              29.707249
            ],
            [
              -83.907771,
              29.036305
            ],
            [
              -83.52045,
              28.936134
            ]
          ]
        ]
      }
    },
    {
      "type": "Feature",
      "properties": {
        "id": 35,
        "sector_name": "Torry",
        "shape": "Polygon"
      },
      "geometry": {
        "type": "Polygon",
        "coordinates": [
          [
            [
              -79.896467,
              29.817447
            ],
            [
              -79.281156,
              30.196041
            ],
            [
              -79.276722,
              30.198754
            ],
            [
              -77.218853,
              29.992223
            ],
            [
              -77.003943,
              29.992223
            ],
            [
              -77.008887,
              31.352137
            ],
            [
              -79.260492,
              32.002505
            ],
            [
              -79.295621,
              31.999
            ],
            [
              -79.696119,
              30.578741
            ],
            [
              -79.696204,
              30.578414
            ],
            [
              -79.691344,
              30.5784
            ],
            [
              -79.896467,
              29.817447
            ]
          ]
        ]
      }
    },
    {
      "type": "Feature",
      "properties": {
        "id": 52,
        "sector_name": "Metta",
        "shape": "Polygon"
      },
      "geometry": {
        "type": "Polygon",
        "coordinates": [
          [
            [
              -77.008879,
              31.352135
            ],
            [
              -77.012209,
              32.254502
            ],
            [
              -76.772502,
              32.957759
            ],
            [
              -78.115192,
              33.971385
            ],
            [
              -78.115686,
              33.967946
            ],
            [
              -78.140483,
              33.837598
            ],
            [
              -78.388456,
              33.837598
            ],
            [
              -79.140638,
              32.516256
            ],
            [
              -79.309919,
              32.00509
            ],
            [
              -79.295621,
              31.999
            ],
            [
              -79.260492,
              32.002505
            ],
            [
              -77.008879,
              31.352135
            ]
          ]
        ]
      }
    },
    {
      "type": "Feature",
      "properties": {
        "id": 78,
        "sector_name": "Lake City",
        "shape": "Polygon"
      },
      "geometry": {
        "type": "Polygon",
        "coordinates": [
          [
            [
              -82.867456,
              29.541988
            ],
            [
              -82.86955,
              29.518759
            ],
            [
              -82.869587,
              29.518984
            ],
            [
              -82.900519,
              29.674039
            ],
            [
              -83.21424,
              30.403019
            ],
            [
              -83.214286,
              30.403127
            ],
            [
              -83.156757,
              30.407459
            ],
            [
              -83.036904,
              30.457348
            ],
            [
              -82.780666,
              30.937104
            ],
            [
              -82.648414,
              30.745488
            ],
            [
              -82.098742,
              30.357545
            ],
            [
              -81.844055,
              29.513883
            ],
            [
              -81.843664,
              29.512583
            ],
            [
              -81.843239,
              29.511504
            ],
            [
              -81.842504,
              29.509622
            ],
            [
              -81.867301,
              29.358447
            ],
            [
              -82.491365,
              29.28638
            ],
            [
              -82.867456,
              29.541988
            ]
          ]
        ]
      }
    },
    {
      "type": "Feature",
      "properties": {
        "id": 34,
        "sector_name": "Seminole",
        "shape": "Polygon"
      },
      "geometry": {
        "type": "Polygon",
        "coordinates": [
          [
            [
              -85.88342,
              31.704116
            ],
            [
              -85.158101,
              30.715291
            ],
            [
              -84.916062,
              30.452464
            ],
            [
              -84.915795,
              30.452383
            ],
            [
              -84.384221,
              30.289764
            ],
            [
              -83.57591,
              30.368101
            ],
            [
              -83.577234,
              30.369824
            ],
            [
              -83.826283,
              30.701966
            ],
            [
              -84.15278,
              31.667189
            ],
            [
              -84.155511,
              31.675318
            ],
            [
              -85.305851,
              31.533427
            ],
            [
              -85.582754,
              31.769142
            ],
            [
              -85.880321,
              31.705874
            ],
            [
              -85.88342,
              31.704116
            ]
          ]
        ]
      }
    },
    {
      "type": "Feature",
      "properties": {
        "id": 33,
        "sector_name": "Geneva",
        "shape": "Polygon"
      },
      "geometry": {
        "type": "Polygon",
        "coordinates": [
          [
            [
              -84.155497,
              31.67532
            ],
            [
              -84.155344,
              31.67482
            ],
            [
              -83.826283,
              30.701966
            ],
            [
              -83.57602,
              30.368203
            ],
            [
              -83.575933,
              30.368098
            ],
            [
              -83.556686,
              30.369963
            ],
            [
              -83.206352,
              30.403895
            ],
            [
              -83.156757,
              30.407459
            ],
            [
              -83.036904,
              30.457348
            ],
            [
              -82.785711,
              30.927681
            ],
            [
              -82.788416,
              30.933883
            ],
            [
              -83.115429,
              31.681258
            ],
            [
              -84.107318,
              31.681258
            ],
            [
              -84.155497,
              31.67532
            ]
          ]
        ]
      }
    },
    {
      "type": "Feature",
      "properties": {
        "id": 47,
        "sector_name": "Summer",
        "shape": "Polygon"
      },
      "geometry": {
        "type": "Polygon",
        "coordinates": [
          [
            [
              -79.309899,
              32.005081
            ],
            [
              -79.309757,
              32.005504
            ],
            [
              -79.140638,
              32.516256
            ],
            [
              -78.388456,
              33.837598
            ],
            [
              -78.140483,
              33.837598
            ],
            [
              -78.115686,
              33.967946
            ],
            [
              -78.115202,
              33.971392
            ],
            [
              -78.772813,
              34.463492
            ],
            [
              -79.326618,
              34.436228
            ],
            [
              -79.719241,
              34.718663
            ],
            [
              -79.724484,
              34.722598
            ],
            [
              -79.729573,
              34.715266
            ],
            [
              -80.86198,
              32.7842
            ],
            [
              -80.862751,
              32.782783
            ],
            [
              -80.225517,
              32.394198
            ],
            [
              -79.309899,
              32.005081
            ]
          ]
        ]
      }
    },
    {
      "type": "Feature",
      "properties": {
        "id": 50,
        "sector_name": "Allma",
        "shape": "Polygon"
      },
      "geometry": {
        "type": "Polygon",
        "coordinates": [
          [
            [
              -82.648414,
              30.745488
            ],
            [
              -82.098742,
              30.357545
            ],
            [
              -82.050584,
              30.19857
            ],
            [
              -82.050539,
              30.198707
            ],
            [
              -81.950992,
              30.463582
            ],
            [
              -81.558369,
              30.819163
            ],
            [
              -81.54597,
              31.066405
            ],
            [
              -81.591432,
              31.275041
            ],
            [
              -81.500509,
              31.465592
            ],
            [
              -81.500509,
              32.027911
            ],
            [
              -81.409585,
              32.384601
            ],
            [
              -81.417547,
              32.389444
            ],
            [
              -81.897264,
              32.680771
            ],
            [
              -81.942726,
              32.55197
            ],
            [
              -82.335349,
              32.15746
            ],
            [
              -83.09993,
              31.683896
            ],
            [
              -83.115429,
              31.681258
            ],
            [
              -82.785711,
              30.927682
            ],
            [
              -82.780666,
              30.937104
            ],
            [
              -82.648414,
              30.745488
            ]
          ]
        ]
      }
    },
    {
      "type": "Feature",
      "properties": {
        "id": 66,
        "sector_name": "Aiken",
        "shape": "Polygon"
      },
      "geometry": {
        "type": "Polygon",
        "coordinates": [
          [
            [
              -81.409585,
              32.384601
            ],
            [
              -81.897264,
              32.680771
            ],
            [
              -81.843537,
              32.890111
            ],
            [
              -81.839404,
              33.895936
            ],
            [
              -81.583166,
              34.296358
            ],
            [
              -81.240138,
              34.426001
            ],
            [
              -80.471423,
              34.752627
            ],
            [
              -80.140794,
              34.851042
            ],
            [
              -79.909353,
              34.861216
            ],
            [
              -79.724483,
              34.722597
            ],
            [
              -79.724672,
              34.722327
            ],
            [
              -79.729573,
              34.715266
            ],
            [
              -80.86198,
              32.7842
            ],
            [
              -80.862754,
              32.782785
            ],
            [
              -80.86508,
              32.7842
            ],
            [
              -81.394087,
              32.401178
            ],
            [
              -81.409585,
              32.384601
            ]
          ]
        ]
      }
    }
  ]
}